stroopwafel/__init__.py
stroopwafel/classes.py
stroopwafel/constants.py
stroopwafel/distributions.py
stroopwafel/genais.py
stroopwafel/prior.py
stroopwafel/sampler.py
stroopwafel/sw.py
stroopwafel/utils.py
tests/__init__.py
tests/bh_bh_merges_in_hubble_time.py
tests/interface_genais.py
tests/ns_ns_merges_in_hubble_time.py
tests/ns_ns_with_kick_sampling.py
tests/traditional_sampling.py
stroopwafel-1.1.0.dist-info/LICENSE
stroopwafel-1.1.0.dist-info/METADATA
stroopwafel-1.1.0.dist-info/WHEEL
stroopwafel-1.1.0.dist-info/top_level.txt
stroopwafel-1.1.0.dist-info/RECORD
