Metadata-Version: 2.1
Name: stroopwafel
Version: 1.1.0
Summary: A python package for STROOPWAFEL and GenAIS algorithms
Home-page: https://github.com/lokiysh/stroopwafel
Author: Lokesh Khandelwal
Author-email: lokesh.khandelwal92@gmail.com
License: UNKNOWN
Platform: UNKNOWN
Classifier: Programming Language :: Python :: 3
Classifier: License :: OSI Approved :: MIT License
Classifier: Operating System :: OS Independent
Requires-Python: >=3
Requires-Dist: numpy
Requires-Dist: scipy
